ohppipeline/__init__.py
ohppipeline/spectral/__init__.py
ohppipeline/spectral/calibration.py
ohppipeline/spectral/data/calibration_tables.dat
ohppipeline/utils/__init__.py
ohppipeline/utils/imageprocessing.py
ohppipeline/utils/utils.py
ohppipeline-1.1.3.dist-info/LICENCE.txt
ohppipeline-1.1.3.dist-info/METADATA
ohppipeline-1.1.3.dist-info/WHEEL
ohppipeline-1.1.3.dist-info/top_level.txt
ohppipeline-1.1.3.dist-info/RECORD
