Metadata-Version: 2.1
Name: ohppipeline
Version: 1.1.3
Summary: UNKNOWN
Home-page: UNKNOWN
Author: Clement Hottier, Noel Robichon
License: UNKNOWN
Platform: UNKNOWN
License-File: LICENCE.txt
Requires-Dist: ccdproc (>=2.0.1)
Requires-Dist: cython (>=0.29.15)
Requires-Dist: numpy (>=1.18.1)
Requires-Dist: astropy (>=3.2.3)
Requires-Dist: scipy (>=1.4.1)
Requires-Dist: pandas (>=0.25.3)
Requires-Dist: tqdm (>=4.19.8)
Requires-Dist: astroalign (>=2.3.1)
